epygenetics/__init__.py
epygenetics/crossover.py
epygenetics/generation.py
epygenetics/genetic_optimizer.py
epygenetics/log.py
epygenetics/mutation.py
epygenetics/selection.py
epygenetics/swarm_optimizer.py
epygenetics/target_functions.py
epygenetics/utils.py
epygenetics-0.1.1.dist-info/licenses/LICENSE
examples/example_genetic.py
examples/example_swarm.py
test/__init__.py
test/test_crossover.py
test/test_generation.py
test/test_utils.py
epygenetics-0.1.1.dist-info/METADATA
epygenetics-0.1.1.dist-info/WHEEL
epygenetics-0.1.1.dist-info/top_level.txt
epygenetics-0.1.1.dist-info/RECORD
